AUTHORS.rst
CONTRIBUTING.rst
HISTORY.rst
LICENSE
MANIFEST.in
README.rst
setup.cfg
setup.py
docs/Makefile
docs/authors.rst
docs/conf.py
docs/contributing.rst
docs/history.rst
docs/index.rst
docs/installation.rst
docs/make.bat
docs/readme.rst
docs/usage.rst
pyyapi_sdk/__init__.py
pyyapi_sdk/cli.py
pyyapi_sdk/pyyapi_sdk.py
pyyapi_sdk.egg-info/PKG-INFO
pyyapi_sdk.egg-info/SOURCES.txt
pyyapi_sdk.egg-info/dependency_links.txt
pyyapi_sdk.egg-info/entry_points.txt
pyyapi_sdk.egg-info/not-zip-safe
pyyapi_sdk.egg-info/top_level.txt
tests/__init__.py
tests/test_pyyapi_sdk.py